{
  "heteronyms": [
    {
      "bopomofo": "ㄇㄧㄥˊ",
      "definitions": [
        {
          "def": "幽暗。",
          "example": [
            "如：「幽冥」。"
          ],
          "quote": [
            "《漢書．卷二七．五行志下之上》：「夷伯，世大夫，正晝雷，其廟獨冥。」"
          ],
          "type": "形"
        },
        {
          "def": "愚昧、不明事理。",
          "example": [
            "如：「冥頑不靈」。"
          ],
          "type": "形"
        },
        {
          "def": "與人死後有關的。",
          "example": [
            "如：「冥婚」、「冥器」。"
          ],
          "type": "形"
        },
        {
          "def": "遠離。",
          "quote": [
            "晉．陶淵明〈辛丑歲七月赴假還江陵夜行塗中〉詩：「閑居三十載，遂與塵事冥。」"
          ],
          "type": "動"
        },
        {
          "def": "暗合、默契。",
          "quote": [
            "魏．高允〈徵士頌〉：「神與理冥，形隨流浪。」"
          ],
          "type": "動"
        },
        {
          "def": "地獄。",
          "example": [
            "如：「唐太宗入冥記」。"
          ],
          "quote": [
            "《後漢書．卷二八下．馮衍傳》：「傷誠善之無辜兮，齎此恨而入冥。」"
          ],
          "type": "名"
        },
        {
          "def": "海。",
          "quote": [
            "《莊子．逍遙遊》：「北冥有魚，其名為鯤，鯤之大不知其幾千里也。」"
          ],
          "type": "名"
        },
        {
          "def": "姓。如漢代有冥都。",
          "type": "名"
        }
      ],
      "pinyin": "míng"
    }
  ],
  "non_radical_stroke_count": 8,
  "radical": "冖",
  "stroke_count": 10,
  "title": "冥"
}