{
  "heteronyms": [
    {
      "bopomofo": "ㄍㄡ",
      "definitions": [
        {
          "def": "彎曲的物體。",
          "example": [
            "如：「衣勾」、「魚勾」。"
          ],
          "link": [
            "同「鉤」。"
          ],
          "type": "名"
        },
        {
          "def": "一種書寫符號，表示刪除、截取或答案正確。",
          "example": [
            "如：「書寫正確的請打勾。」"
          ],
          "type": "名"
        },
        {
          "def": "姓。如宋代有勾濤。",
          "type": "名"
        },
        {
          "def": "挑動、引起。",
          "quote": [
            "元．張可久〈醉太平．金華洞冷〉曲：「數枝黃菊勾詩興，一川紅葉迷仙徑。」",
            "《紅樓夢．第九五回》：「偶沾寒氣，勾起舊病。」"
          ],
          "type": "動"
        },
        {
          "def": "選取、徵調。",
          "quote": [
            "元．石君寶《秋胡戲妻．第一折》：「今奉上司差遣，著我勾秋胡當軍，走一遭去。」"
          ],
          "type": "動"
        },
        {
          "def": "刪掉、取消。",
          "example": [
            "如：「新愁舊恨，一筆勾銷。」"
          ],
          "quote": [
            "元．關漢卿《竇娥冤．第一折》：「舊恩愛一筆勾，新夫妻兩意投，枉教人笑破口。」"
          ],
          "type": "動"
        },
        {
          "def": "暗地相通。",
          "example": [
            "如：「勾結」。"
          ],
          "quote": [
            "《喻世明言．卷四○．沈小霞相會出師表》：「沈鍊因失職 怨望，教浩等煽妖作幻，勾虜謀逆。」"
          ],
          "type": "動"
        },
        {
          "def": "描繪。",
          "example": [
            "如：「勾勒」、「勾出輪廓來。」"
          ],
          "type": "動"
        },
        {
          "def": "一種烹飪方法。用芡粉或麵粉使菜餚、湯汁濃稠。",
          "example": [
            "如：「勾滷」、「勾芡」。"
          ],
          "type": "動"
        }
      ],
      "pinyin": "gōu"
    },
    {
      "bopomofo": "ㄍㄡˋ",
      "definitions": [
        {
          "def": "探取。",
          "example": [
            "如：「他伸長了手去勾架上的書。」"
          ],
          "type": "動"
        },
        {
          "def": "足夠。",
          "link": [
            "同「夠」。"
          ],
          "quote": [
            "元．馬致遠《漢宮秋．第一折》：「刷選室女，已選勾九十九名。」"
          ],
          "type": "副"
        }
      ],
      "pinyin": "gòu"
    }
  ],
  "non_radical_stroke_count": 2,
  "radical": "勹",
  "stroke_count": 4,
  "title": "勾"
}