{
  "heteronyms": [
    {
      "bopomofo": "ㄏㄤ",
      "definitions": [
        {
          "def": "用來敲打地基，使其結實的工具。",
          "example": [
            "如：「木夯」、「石夯」、「鐵夯」。"
          ],
          "type": "名"
        },
        {
          "def": "脹滿、鼓脹。",
          "quote": [
            "元．石君寶《秋胡戲妻．第四折》：「怎敢來俺莊上，不由的忿氣夯胸膛。」",
            "元．關漢卿《調風月．第二折》：「氣夯破肚別人行怎又不敢提？獨自向銀蟾底。」"
          ],
          "type": "動"
        },
        {
          "def": "北方方言。指用力以肩扛物。",
          "example": [
            "如：「夯行李」。"
          ],
          "quote": [
            "明．凈善重集．禪林寶訓一：「自家閨閣中物不肯放下，返累及他人擔夯，無乃大勞乎！」"
          ],
          "type": "動"
        },
        {
          "def": "用夯砸地。",
          "example": [
            "如：「夯實」、「夯地」。"
          ],
          "type": "動"
        }
      ],
      "pinyin": "hāng"
    }
  ],
  "non_radical_stroke_count": 2,
  "radical": "大",
  "stroke_count": 5,
  "title": "夯"
}