{
  "heteronyms": [
    {
      "bopomofo": "ㄕㄨ",
      "definitions": [
        {
          "def": "容貌美麗。",
          "quote": [
            "《詩經．邶風．靜女》：「靜女其姝，俟我於城隅。」",
            "《後漢書．卷一○．皇后紀上．和熹鄧皇后傳》：「后長七尺二寸，姿顏姝麗。」"
          ],
          "type": "形"
        },
        {
          "def": "美女。",
          "quote": [
            "《文選．宋玉．登徒子好色賦》：「此郊之姝，華色含光。」",
            "《聊齋志異．卷一一．書痴》：「下几亭亭，宛然絕代之姝。」"
          ],
          "type": "名"
        }
      ],
      "pinyin": "shū"
    }
  ],
  "non_radical_stroke_count": 6,
  "radical": "女",
  "stroke_count": 9,
  "title": "姝"
}