{
  "heteronyms": [
    {
      "bopomofo": "ㄩˇ",
      "definitions": [
        {
          "def": "屋簷。",
          "quote": [
            "《易經．繫辭下》：「上古穴居而野處，後世聖人易之以宮室，上棟下宇，以待風雨，蓋取之大壯。」"
          ],
          "type": "名"
        },
        {
          "def": "房屋。",
          "example": [
            "如：「屋宇」。"
          ],
          "quote": [
            "《楚辭．宋玉．招魂》：「高堂邃宇，檻層軒些。」",
            "宋．蘇軾〈水調歌頭．明月幾時有〉詞：「我欲乘風歸去，又恐瓊樓玉宇，高處不勝寒。」"
          ],
          "type": "名"
        },
        {
          "def": "疆域、國境。",
          "quote": [
            "《左傳．昭公四年》：「或無難以喪其國，失其守宇。」",
            "《文選．枚乘．七發》：「今時天下安寧，四宇和平。」"
          ],
          "type": "名"
        },
        {
          "def": "上下四方，為整個空間的總稱。",
          "example": [
            "如：「宇宙」、「寰宇」。"
          ],
          "quote": [
            "《荀子．富國》：「萬物同宇而異體，無宜而有用。」"
          ],
          "type": "名"
        },
        {
          "def": "人的儀表、風度。",
          "example": [
            "如：「眉宇」、「氣宇軒昂」。"
          ],
          "quote": [
            "《晉書．卷七九．謝安傳》：「神識沉敏，風宇條暢。」"
          ],
          "type": "名"
        }
      ],
      "pinyin": "yǔ"
    }
  ],
  "non_radical_stroke_count": 3,
  "radical": "宀",
  "stroke_count": 6,
  "title": "宇"
}