{
  "heteronyms": [
    {
      "bopomofo": "ㄉㄧˋ",
      "definitions": [
        {
          "def": "稱謂：(1)稱同胞男子先生者為「兄」，後生者為「弟」。如：「么弟」、「胞弟」、「令弟」、「舍弟」。《左傳．隱公元年》：「蔓草猶不可除，況君之寵弟乎？」也稱為「弟弟」。(2)稱親戚中同輩而年紀比自己小的男子。如：「堂弟」、「表弟」、「妻弟」、「族弟」。(3)古代亦稱女子後生者為「弟」。即妹。《孟子．萬章上》：「於衛主讎由彌子之妻，與子路之妻兄弟也。」《史記．卷五十六．陳丞相世家》：「樊噲，帝之故人也，功多，且及乃呂后弟呂嬃之夫。」(4)對同輩朋友的自稱。如：「愚弟」、「閣下海量，小弟自嘆弗如！」《紅樓夢．第二回》：「雨村忙亦笑問：『老兄何日到此，弟竟不知。』」(5)稱年少於己者的同輩朋友。如：「仁弟」、「賢弟」。",
          "type": "名"
        },
        {
          "def": "次序、等第。",
          "quote": [
            "《呂氏春秋．貴直論．原亂》：「亂必有弟：大亂五、小亂三。」",
            "《漢書．卷八三．朱博傳》：「徙雲陽、平陵縣，以高弟入為長安令。」"
          ],
          "type": "名"
        },
        {
          "def": "門徒、學生。",
          "example": [
            "如：「弟子」、「徒弟」。"
          ],
          "quote": [
            "唐．賈至〈工部侍郎李公集序〉：「可謂孔門之弟，洙泗遺徒。」"
          ],
          "type": "名"
        }
      ],
      "pinyin": "dì"
    },
    {
      "bopomofo": "ㄊㄧˋ",
      "definitions": [
        {
          "def": "儒家稱敬順兄長、友愛兄弟的倫理道德為「弟」。",
          "link": [
            "同「悌」。"
          ],
          "quote": [
            "《禮記．大學》：「孝者所以事君也，弟者所以事長也。」"
          ],
          "type": "名"
        },
        {
          "def": "敬愛兄長。",
          "link": [
            "同「悌」。"
          ],
          "quote": [
            "《論語．學而》：「其為人也孝弟，而好犯上者鮮矣。」"
          ],
          "type": "動"
        },
        {
          "def": "但、且。",
          "quote": [
            "《史記．卷一．五帝本紀．太史公曰》：「顧弟弗深考，其所表見皆不虛。」"
          ],
          "type": "副"
        }
      ],
      "pinyin": "tì"
    }
  ],
  "non_radical_stroke_count": 4,
  "radical": "弓",
  "stroke_count": 7,
  "title": "弟"
}