{
  "heteronyms": [
    {
      "bopomofo": "ㄓㄠˇ",
      "definitions": [
        {
          "def": "探訪、尋求。",
          "example": [
            "如：「找朋友」、「找工作」、「自找麻煩」。"
          ],
          "quote": [
            "《紅樓夢．第三一回》：「這可丟了！往那裡找去？」"
          ],
          "type": "動"
        },
        {
          "def": "補回差額。",
          "example": [
            "如：「找錢」、「找零兒」。"
          ],
          "quote": [
            "《警世通言．卷一一．蘇知縣羅衫再合》：「當下先秤了一半船錢，那一半直待到縣時找足。」"
          ],
          "type": "動"
        }
      ],
      "pinyin": "zhǎo"
    }
  ],
  "non_radical_stroke_count": 4,
  "radical": "手",
  "stroke_count": 7,
  "title": "找"
}