{
  "heteronyms": [
    {
      "bopomofo": "ㄅㄨˇ",
      "definitions": [
        {
          "def": "捉拿、擒住。",
          "example": [
            "如：「逮捕」、「緝捕」、「拒捕」、「拘捕」。"
          ],
          "quote": [
            "《文選．張衡．四愁 詩．序》：「下吏收捕，盡服擒諸豪俠。」"
          ],
          "type": "動"
        },
        {
          "def": "獵取。",
          "quote": [
            "《文選．揚雄．長楊賦》：「張羅罔罝罘，捕熊羆豪豬。」",
            "《文選．束晳．補亡詩六首之一》：「淩波赴汨，噬魴捕鯉。」"
          ],
          "type": "動"
        },
        {
          "def": "古代的基層治安人員。",
          "example": [
            "如：「巡捕」、「捕快」。"
          ],
          "type": "名"
        },
        {
          "def": "姓。如漢代有捕巡。",
          "type": "名"
        }
      ],
      "pinyin": "bǔ"
    },
    {
      "bopomofo": "（又音）ㄅㄨˋ",
      "definitions": [
        {
          "def": "(一)之又音。"
        }
      ],
      "pinyin": "（又音）bù"
    }
  ],
  "non_radical_stroke_count": 7,
  "radical": "手",
  "stroke_count": 10,
  "title": "捕"
}