{
  "heteronyms": [
    {
      "bopomofo": "ㄕㄚ",
      "definitions": [
        {
          "def": "以刀或武器使人或禽獸等失去生命。",
          "example": [
            "如：「殺人放火」、「殺豬宰羊」。"
          ],
          "type": "動"
        },
        {
          "def": "戰鬥。",
          "example": [
            "如：「殺出重圍」。"
          ],
          "quote": [
            "《三國演義．第五回》：「殺至天明，雄方引兵上關。」"
          ],
          "type": "動"
        },
        {
          "def": "敗壞。",
          "example": [
            "如：「殺風景」。"
          ],
          "type": "動"
        },
        {
          "def": "減省。",
          "example": [
            "如：「殺價」。"
          ],
          "type": "動"
        }
      ],
      "pinyin": "shā"
    },
    {
      "bopomofo": "ㄕㄚˋ",
      "definitions": [
        {
          "def": "甚、極。",
          "example": [
            "如：「愁殺人」。"
          ],
          "link": [
            "同「煞」。"
          ],
          "quote": [
            "元．張養浩〈詠江南．一江煙水照晴嵐〉曲：「畫船兒天邊至，酒旗兒風外颭，愛殺江南。」"
          ],
          "type": "副"
        }
      ],
      "pinyin": "shà"
    },
    {
      "bopomofo": "ㄕㄞˋ",
      "definitions": [
        {
          "def": "等差。",
          "quote": [
            "《禮記．文王世子》：「其族食世降一等，親親之殺也。」",
            " 漢．鄭玄．注：「殺，差也。」"
          ],
          "type": "名"
        },
        {
          "def": "減、削。",
          "quote": [
            "《周禮．地官．廩人》：「若食不能人二釜，則令邦移民就穀，詔王殺邦用。」",
            "漢．鄭玄．注：「殺，猶減也。」"
          ],
          "type": "動"
        },
        {
          "def": "衰微。",
          "quote": [
            "《呂氏春秋．恃君覽．長利》：「是故地日削，子孫彌殺。」",
            "漢．高誘．注：「殺，衰也。」"
          ],
          "type": "動"
        },
        {
          "def": "細小。",
          "quote": [
            "《呂氏春秋．士容論．審時》：「先時者，大本而華，莖殺而不遂，葉稿短穗。後時者，小莖而麻長，短穗而厚糠，小米鉗而不香。」"
          ],
          "type": "形"
        }
      ],
      "pinyin": "shài"
    }
  ],
  "non_radical_stroke_count": 7,
  "radical": "殳",
  "stroke_count": 11,
  "title": "殺"
}