{
  "heteronyms": [
    {
      "bopomofo": "ㄆㄠˋ",
      "definitions": [
        {
          "def": "在水面上漂浮，內含氣體的球狀物。大的稱為「泡」，小的稱為「沫」。",
          "example": [
            "如：「泡沫」、「水泡」。"
          ],
          "type": "名"
        },
        {
          "def": "指泡狀的東西。",
          "example": [
            "如：「肥皂泡」、「電燈泡」。"
          ],
          "type": "名"
        },
        {
          "def": "因皮膚受傷而起的水泡。",
          "example": [
            "如：「他的大腿被熱水燙到，已經起泡了。」"
          ],
          "quote": [
            "《水滸傳．第八回》：「林冲走不到三二里，腳上泡被新草鞋打破了，鮮血淋漓，正走不動。」"
          ],
          "type": "名"
        },
        {
          "def": "量詞：(1) 計算動作次數的單位。相當於「番」、「回」、「陣」。《官場現形記．第四七回》：「童子良經他這一泡恭維，便覺他說的話，果然不錯。」(2) 計算茶葉沖浸次數的單位。如：「這茶已經是第二泡。」",
          "type": "名"
        },
        {
          "def": "用水沖浸。",
          "example": [
            "如：「泡飯」、「泡茶」、「泡衣服」。"
          ],
          "type": "動"
        },
        {
          "def": "消磨、耽擱或故意糾纏。",
          "example": [
            "如：「泡時間」、「你別在這裡瞎泡了。」、「他是泡妞高手。」"
          ],
          "type": "動"
        }
      ],
      "pinyin": "pào"
    },
    {
      "bopomofo": "ㄆㄠ",
      "definitions": [
        {
          "def": "量詞。計算屎尿的單位。",
          "example": [
            "如：「撒一泡尿」。"
          ],
          "type": "名"
        },
        {
          "def": "鼓起且鬆軟的東西。",
          "example": [
            "如：「眼泡兒」、「豆腐泡兒」。"
          ],
          "type": "名"
        },
        {
          "def": "地名用字。小湖泊的意思。如大陸地區黑龍江省有蓮花泡、吉林省有月亮泡。",
          "type": "名"
        },
        {
          "def": "膨鬆、腫脹。參見「泡泡」條。",
          "type": "形"
        }
      ],
      "pinyin": "pāo"
    }
  ],
  "non_radical_stroke_count": 5,
  "radical": "水",
  "stroke_count": 8,
  "title": "泡"
}