{
  "heteronyms": [
    {
      "bopomofo": "ㄏㄨㄟˊ",
      "definitions": [
        {
          "def": "蜿蜒曲折的水道。",
          "quote": [
            "《詩經．秦風．蒹葭》：「溯洄從之，道阻且長。」",
            "唐．李白〈送別〉詩：「尋陽五溪水，沿洄直入巫山裡。」"
          ],
          "type": "名"
        },
        {
          "def": "水流盤旋迴轉的。",
          "quote": [
            "《後漢書．卷七六．循吏傳．王景傳》：「十里立一水門，令更相洄注，無復潰漏之患。」"
          ],
          "type": "副"
        }
      ],
      "pinyin": "huí"
    }
  ],
  "non_radical_stroke_count": 6,
  "radical": "水",
  "stroke_count": 9,
  "title": "洄"
}