{
  "heteronyms": [
    {
      "bopomofo": "ㄗㄠˇ",
      "definitions": [
        {
          "def": "有水藻花紋的玉飾。",
          "quote": [
            "《說文解字．玉部》：「璪，玉飾如水藻之文。」"
          ],
          "type": "名"
        },
        {
          "def": "古代掛在帽上的裝飾品。以五彩絲線穿串玉石而成。",
          "quote": [
            "《禮記．郊特牲》：「戴冕璪十有二旒，則天數也。」",
            "清．孫希旦．集解：「璪者，用五采絲為繩，垂之以為冕之旒也。」"
          ],
          "type": "名"
        }
      ],
      "pinyin": "zǎo"
    }
  ],
  "non_radical_stroke_count": 13,
  "radical": "玉",
  "stroke_count": 17,
  "title": "璪"
}