{
  "heteronyms": [
    {
      "bopomofo": "ㄇㄨˇ",
      "definitions": [
        {
          "def": "量詞。計算面積的單位。一公畝等於一百平方公尺，一市畝等於六千平方市尺。古代以縱橫五尺為方步，二百四十方步為畝。",
          "quote": [
            "《孟子．梁惠王上》：「五畝之宅，樹之以桑，五十者可以衣帛矣。」"
          ],
          "type": "名"
        },
        {
          "def": "田壟，田中高起的地方。",
          "quote": [
            "《詩經．小雅．信南山》：「我疆我理，南東其畝。」"
          ],
          "type": "名"
        }
      ],
      "pinyin": "mǔ"
    },
    {
      "bopomofo": "（又音）ㄇㄡˇ",
      "definitions": [
        {
          "def": "(一)之又音。"
        }
      ],
      "pinyin": "（又音）mǒu"
    }
  ],
  "non_radical_stroke_count": 5,
  "radical": "田",
  "stroke_count": 10,
  "title": "畝"
}