{
  "heteronyms": [
    {
      "bopomofo": "ㄒㄧ",
      "definitions": [
        {
          "def": "看、望。",
          "quote": [
            "《文選．古詩十九首．凜凜歲云暮》：「眄睞以適意，引領遙相睎。」",
            "《文選．班固．西都賦》：「於是睎秦嶺，睋北阜。」"
          ],
          "type": "動"
        },
        {
          "def": "仰慕。",
          "quote": [
            "唐．柳宗元〈貞符詩．序〉：「人皆漻然休然，相睎以生，相持以成。」",
            "宋．曾鞏〈寄歐陽舍人書〉：「其追睎祖德，而思所以傳之之繇。」"
          ],
          "type": "動"
        }
      ],
      "pinyin": "xī"
    }
  ],
  "non_radical_stroke_count": 7,
  "radical": "目",
  "stroke_count": 12,
  "title": "睎"
}