{
  "heteronyms": [
    {
      "bopomofo": "ㄙㄨㄟˋ",
      "definitions": [
        {
          "def": "眼光清明的樣子。",
          "quote": [
            "明．張自烈《正字通．目部》：「睟，目清明也。」"
          ],
          "type": "形"
        },
        {
          "def": "潤澤的樣子。",
          "quote": [
            "唐．元稹《鶯鶯傳》：「常服睟容，不加新飾。」"
          ],
          "type": "形"
        },
        {
          "def": "顏色純一的樣子。",
          "quote": [
            "漢．揚雄《法言．君子》：「牛玄騂白睟而角，其升諸廟乎。」",
            "唐．李德裕〈唐武宗皇帝真容贊〉：「至於天光睟清，日華明潤，非可圖也。」"
          ],
          "type": "形"
        }
      ],
      "pinyin": "suì"
    }
  ],
  "non_radical_stroke_count": 8,
  "radical": "目",
  "stroke_count": 13,
  "title": "睟"
}