{
  "heteronyms": [
    {
      "bopomofo": "ㄑㄧˊ",
      "definitions": [
        {
          "def": "曲折的堤岸。",
          "quote": [
            "《玉篇．石部》：「碕，曲岸頭。」",
            "《楚辭．劉向．九歎．離世》：「遵江曲之逶移兮，觸石碕而衡遊。」",
            "《漢書．卷八七．揚雄傳上》：「探巖排碕，薄索蛟螭。」"
          ],
          "type": "名"
        },
        {
          "def": "彎曲。",
          "quote": [
            "南朝宋．鮑照〈登大雷岸與妹書〉：「碪石為之摧碎，碕岸為之齏落。」"
          ],
          "type": "形"
        }
      ],
      "pinyin": "qí"
    }
  ],
  "non_radical_stroke_count": 8,
  "radical": "石",
  "stroke_count": 13,
  "title": "碕"
}