{
  "heteronyms": [
    {
      "bopomofo": "ㄉㄨㄢ",
      "definitions": [
        {
          "def": "事物的兩頭皆稱為「端」。",
          "example": [
            "如：「尖端」、「末端」、「筆端」。"
          ],
          "quote": [
            "《論語．子罕》：「我叩其兩端而竭焉。」"
          ],
          "type": "名"
        },
        {
          "def": "事物的起始。",
          "example": [
            "如：「開端」、「發端」、「挑起戰端」。"
          ],
          "quote": [
            "《孟子．公孫丑》：「惻隱之心，仁之端也。」"
          ],
          "type": "名"
        },
        {
          "def": "項目、方面。",
          "example": [
            "如：「鬼計多端」、「變化萬端」、「舉其一端」。"
          ],
          "type": "名"
        },
        {
          "def": "心思、思緒。",
          "quote": [
            "南朝宋．劉義慶《世說新語．言語》：「衛洗馬初欲渡江，形神慘悴語左右云：『見此芒芒，不覺百端交集。』」",
            "唐．杜甫〈自京赴奉先縣詠懷五百字〉詩：「憂端齊終南，澒洞不可掇。」"
          ],
          "type": "名"
        },
        {
          "def": "古代布帛的長度單位。通常一端約等於一疋。",
          "quote": [
            "《初刻拍案驚奇．卷一》：「除了文若虛，每人送緞子二端。」"
          ],
          "type": "名"
        },
        {
          "def": "姓。如明代有端孝思。",
          "type": "名"
        },
        {
          "def": "正、正直。",
          "example": [
            "如：「品行不端」。"
          ],
          "quote": [
            "《禮記．玉藻》：「目容端，口容止。」",
            "《孟子．離婁下》：「夫尹公之他，端人也，其取友必端矣。」"
          ],
          "type": "形"
        },
        {
          "def": "以手托物。",
          "example": [
            "如：「端碗」、「端菜上桌」。"
          ],
          "type": "動"
        },
        {
          "def": "擺。",
          "example": [
            "如：「端架子」、「把問題都端出檯面上討論。」"
          ],
          "type": "動"
        },
        {
          "def": "到底、究竟。",
          "quote": [
            "宋．王安石〈龍泉寺石井〉詩二首之二：「四海旱多霖雨少，此中端有臥龍無？」",
            "宋．陸游〈幽事〉詩：「餘年端有幾？風月且婆娑。」"
          ],
          "type": "副"
        },
        {
          "def": "果真。",
          "quote": [
            "宋．蘇軾〈水龍吟．小舟橫截春江〉詞：「武昌南岸，昔遊應記。料多情夢裡，端來見我，也參差是。」"
          ],
          "type": "副"
        }
      ],
      "pinyin": "duān"
    }
  ],
  "non_radical_stroke_count": 9,
  "radical": "立",
  "stroke_count": 14,
  "title": "端"
}