{
  "heteronyms": [
    {
      "bopomofo": "ㄘㄞˊ",
      "definitions": [
        {
          "def": "方、始、剛剛。",
          "quote": [
            "《漢書．卷四九．鼂錯傳》：「救之，少發則不足，多發，遠縣纔至，則胡又已去。」",
            "唐．魚玄機〈閨怨〉詩：「別日南鴻纔北去，今朝北雁又南飛。」"
          ],
          "type": "副"
        },
        {
          "def": "僅、只。",
          "quote": [
            "《漢書．卷五一．賈山傳》：「然身死纔數月耳，天下四面而攻之，宗廟滅 絕矣。」",
            "元．關漢卿《竇娥冤．第四折》：「至十七歲與夫配合，纔得兩年，不幸兒夫亡化。」"
          ],
          "type": "副"
        }
      ],
      "pinyin": "cái"
    }
  ],
  "non_radical_stroke_count": 17,
  "radical": "糸",
  "stroke_count": 23,
  "title": "纔"
}