{
  "heteronyms": [
    {
      "bopomofo": "ㄈㄨˊ",
      "definitions": [
        {
          "def": "浮腫。",
          "quote": [
            "《集韻．平聲．虞韻》：「胕，腫也。」",
            "《山海經．西山經》：「有草焉，其名曰黃雚，其狀如樗，其葉如麻，白華而赤實，其狀如赭，浴之已疥，又可以已胕。」",
            "晉．郭璞．注：「治胕腫也；音符。」",
            "《黃帝內經素問．卷二○．五常政大論》：「寒熱胕腫。」",
            "唐．王冰．注：「胕腫謂腫滿，按之不起。」"
          ],
          "type": "形"
        }
      ],
      "pinyin": "fú"
    },
    {
      "bopomofo": "ㄈㄨ",
      "definitions": [
        {
          "def": "足。",
          "quote": [
            "《集韻．平聲．虞韻》：「跗，足也。或作胕。」"
          ],
          "type": "名"
        },
        {
          "def": "指皮膚。",
          "link": [
            "同「膚」。"
          ],
          "quote": [
            "《戰國策．楚策四》：「蹄申膝折，尾湛胕潰。」"
          ],
          "type": "名"
        }
      ],
      "pinyin": "fū"
    }
  ],
  "non_radical_stroke_count": 5,
  "radical": "肉",
  "stroke_count": 9,
  "title": "胕"
}