{
  "heteronyms": [
    {
      "bopomofo": "ㄕㄠ",
      "definitions": [
        {
          "def": "船尾。",
          "quote": [
            "《醒世恆言．卷三二．黃秀才徼靈玉馬墜》：「但前艙貨物充滿，只可以艄頭 存生，夜間在火艙歇宿。」",
            "《儒林外史．第五一回》：「在艄上一個夾剪艙底下，拿出一個大口袋來。」"
          ],
          "type": "名"
        },
        {
          "def": "船舵。",
          "example": [
            "如：「掌艄」。"
          ],
          "quote": [
            "《初刻拍案驚奇．卷二二》：「從此只在往來船隻上，替他執艄度日。」"
          ],
          "type": "名"
        }
      ],
      "pinyin": "shāo"
    }
  ],
  "non_radical_stroke_count": 7,
  "radical": "舟",
  "stroke_count": 13,
  "title": "艄"
}