{
  "heteronyms": [
    {
      "bopomofo": "ㄏㄨㄚˊ",
      "definitions": [
        {
          "def": "中國、華夏的簡稱。",
          "quote": [
            "《左傳．定公十年》：「裔不謀夏，夷不亂華。」"
          ],
          "type": "名"
        },
        {
          "def": "光彩、光澤。",
          "quote": [
            "唐．李白〈峨眉山月歌送蜀僧晏入中京〉詩：「黃鶴樓前月華白，此中忽見峨眉客。」",
            "吳代十國南唐．李煜〈秋鶯〉詩：「莫更留連好歸去，露華凄冷蓼花愁。」"
          ],
          "type": "名"
        },
        {
          "def": "時光。",
          "example": [
            "如：「年華」、「韶華」。"
          ],
          "quote": [
            "唐．劉方平〈秋夜泛舟〉詩：「歲華空復晚，鄉思不堪愁。」"
          ],
          "type": "名"
        },
        {
          "def": "文采、文飾。",
          "example": [
            "如：「樸實無華」。"
          ],
          "quote": [
            "南朝梁．劉勰《文心雕龍．徵聖》：「然則聖文之雅麗，固銜華而佩實者也。」"
          ],
          "type": "名"
        },
        {
          "def": "化妝用的粉。",
          "quote": [
            "《文選．曹植．洛神賦》：「芳澤無加，鉛華弗御。」"
          ],
          "type": "名"
        },
        {
          "def": "文章、事物精要的部分。",
          "example": [
            "如：「精華」。"
          ],
          "quote": [
            "唐．韓愈〈進學解〉：「沉浸醲郁，含英咀華。」"
          ],
          "type": "名"
        },
        {
          "def": "中國的。",
          "quote": [
            "《漢書．卷八八．西域傳．贊曰》：「不率華禮，莫有典書。」",
            "《北史．卷三六．薛辯傳》：「於是風化大行，有同華俗。」"
          ],
          "type": "形"
        },
        {
          "def": "美麗有光彩的。",
          "example": [
            "如：「華燈初上」。"
          ],
          "quote": [
            "三國魏．鍾會〈孔雀賦〉：「五色點注，華羽參差。」",
            "《隋書．卷二三．五行志下》：「於仙都苑穿池築山，樓殿間起，窮華極麗。」"
          ],
          "type": "形"
        },
        {
          "def": "繁盛。",
          "example": [
            "如：「繁華」、「榮華」。"
          ],
          "quote": [
            "《史記．卷六八．商君傳》：「有功者顯榮，無功者雖富無所芬華。」"
          ],
          "type": "形"
        },
        {
          "def": "虛空不實的。",
          "quote": [
            "《晉書．卷七五．范汪傳》：「飾華言以翳實，騁繁文以惑世。」"
          ],
          "type": "形"
        },
        {
          "def": "（頭髮）花白。",
          "quote": [
            "《墨子．脩身》：「華髮隳顛，而猶弗舍者，其唯聖人乎！」",
            "宋．陸游〈適閩〉詩：「功名塞外心空壯，詩酒樽前髮已華。」"
          ],
          "type": "形"
        }
      ],
      "pinyin": "huá"
    },
    {
      "bopomofo": "ㄏㄨㄚˋ",
      "definitions": [
        {
          "def": "參見「華山」條。",
          "type": "名"
        },
        {
          "def": "姓。如漢代有華佗。",
          "type": "名"
        }
      ],
      "pinyin": "huà"
    },
    {
      "bopomofo": "ㄏㄨㄚ",
      "definitions": [
        {
          "def": "植物的花朵。",
          "example": [
            "如：「春華秋實」。"
          ],
          "link": [
            "同「花」。"
          ],
          "quote": [
            "《詩經．周南．桃夭》：「桃之夭夭，灼灼其華。」"
          ],
          "type": "名"
        }
      ],
      "pinyin": "huā"
    }
  ],
  "non_radical_stroke_count": 8,
  "radical": "艸",
  "stroke_count": 12,
  "title": "華"
}