{
  "heteronyms": [
    {
      "bopomofo": "ㄑㄧㄣ",
      "definitions": [
        {
          "def": "大被子。",
          "quote": [
            "《詩經．召南．小星》：「肅肅宵征，抱衾同裯。」",
            "唐．白居易〈長恨歌〉：「鴛鴦瓦冷霜華重，翡翠衾寒誰與共？」"
          ],
          "type": "名"
        },
        {
          "def": "殮屍用的被子。",
          "quote": [
            "《孝經．喪親章》：「為之棺椁衣衾而舉之。」",
            "《孟子．梁惠王下》：「謂棺槨衣衾之美也。」"
          ],
          "type": "名"
        }
      ],
      "pinyin": "qīn"
    },
    {
      "bopomofo": "（又音）ㄑㄧㄣˊ",
      "definitions": [
        {
          "def": "(一)之又音。"
        }
      ],
      "pinyin": "（又音）qín"
    }
  ],
  "non_radical_stroke_count": 4,
  "radical": "衣",
  "stroke_count": 10,
  "title": "衾"
}