{
  "heteronyms": [
    {
      "bopomofo": "ㄓㄠˋ",
      "definitions": [
        {
          "def": "告訴、告誡、教導。",
          "quote": [
            "《莊子．盜跖》：「夫為人父者，必能詔其子；為人兄者，必能教其弟。」",
            "《楚辭．屈原．離騷》：「麾蛟龍使梁津合，詔西皇使涉予。」"
          ],
          "type": "動"
        },
        {
          "def": "古時皇帝所頒發的命令。",
          "quote": [
            "《文選．諸葛亮．出師表》：「善道察納雅言，深追先帝遺詔。」",
            "唐．柳宗元〈尚書戶部侍郎王君先太夫人河間劉氏誌文〉：「然而天子有詔，俾定封邑。」"
          ],
          "type": "名"
        }
      ],
      "pinyin": "zhào"
    }
  ],
  "non_radical_stroke_count": 5,
  "radical": "言",
  "stroke_count": 12,
  "title": "詔"
}