{
  "heteronyms": [
    {
      "bopomofo": "ㄩㄥˇ",
      "definitions": [
        {
          "def": "跳、躍。",
          "quote": [
            "《禮記．喪服四制》：「傴者不袒，跛者不踊。」",
            "《文選．曹植．洛神賦》：「鯨鯢踊而夾轂，水禽翔而為衛。」"
          ],
          "type": "動"
        },
        {
          "def": "登上。",
          "quote": [
            "《公羊傳．成公二年》：「踊于棓而窺客，則客或跛或眇。」"
          ],
          "type": "動"
        },
        {
          "def": "物價上漲。",
          "quote": [
            "《史記．卷三○．平準書》：「物踊騰糶，米至石萬錢。」",
            "《舊唐書．卷一三四．馬燧傳》：「物價騰踊，軍乏糧餉。」"
          ],
          "type": "動"
        },
        {
          "def": "古代為被砍斷腳跟的人所特製的鞋子。",
          "quote": [
            "《左傳．昭公三年》：「國之諸市，屨賤踊貴。」",
            "晉．杜預．注：「踊，刖足者屨。」"
          ],
          "type": "名"
        }
      ],
      "pinyin": "yǒng"
    }
  ],
  "non_radical_stroke_count": 7,
  "radical": "足",
  "stroke_count": 14,
  "title": "踊"
}