{
  "heteronyms": [
    {
      "bopomofo": "ㄍㄜˊ",
      "definitions": [
        {
          "def": "遮斷、阻塞。",
          "example": [
            "如：「阻隔」、「分隔」。"
          ],
          "quote": [
            "《說文解字．阜部》：「隔，塞也。」",
            "《後漢書．卷三三．鄭弘傳》：「帝問知其故，遂聽置雲母屏風，分隔其閒。」"
          ],
          "type": "動"
        },
        {
          "def": "距離、間隔。",
          "example": [
            "如：「相隔千里」、「隔兩天再說吧！」。"
          ],
          "quote": [
            "《新唐書．卷一．高祖本紀》：「今江都隔遠，後期奈何？」",
            "唐．李商隱〈無題〉詩：「劉郎已恨蓬山遠，更隔蓬山一萬重。」"
          ],
          "type": "動"
        },
        {
          "def": "改變、變異。",
          "quote": [
            "《續漢書志．第二三．郡國志五》贊曰：「稱號遷隔，封割糾紛。」"
          ],
          "type": "動"
        }
      ],
      "pinyin": "gé"
    }
  ],
  "non_radical_stroke_count": 10,
  "radical": "阜",
  "stroke_count": 13,
  "title": "隔"
}