{
  "heteronyms": [
    {
      "bopomofo": "ㄎㄨㄤˊ",
      "definitions": [
        {
          "def": "動物名：(1)夢鳥。鳳屬。具五彩羽毛，頭有冠。《玉篇．鳥部》：「鵟，鳥，有冠。」《爾雅．釋鳥》：「狂，夢鳥。」唐．陸德明《經典釋文．卷三○．爾雅音義下》：「鵟，本今作狂。」(2)貓頭鷹。《廣韻．平聲．陽韻》：「鵟，鴟屬。」《爾雅．釋鳥》：「狂，茅鴟。」清．郝懿行．義疏：「茅鴟，即今貓兒頭，其頭似貓，大目，有毛角。……，揚州謂之夜貓。善笑，俗人聞其笑聲，云有凶禍也。」(3)一種狀似老鷹的鳥。羽毛褐色，尾部稍淡。常在高空飛翔。以鼠類為食，是田間的益鳥。俗稱為「土豹」。",
          "type": "名"
        }
      ],
      "pinyin": "kuáng"
    }
  ],
  "non_radical_stroke_count": 7,
  "radical": "鳥",
  "stroke_count": 18,
  "title": "鵟"
}