{
  "heteronyms": [
    {
      "bopomofo": "ㄕㄥˋ　ㄉㄨㄛ　ㄇㄟˇ　ㄐㄧˊ　ㄆㄨˇ　ㄌㄧㄣˊ　ㄒㄧ　ㄅㄧˇ　ㄇㄧㄣˊ　ㄓㄨˇ　ㄍㄨㄥˋ　ㄏㄜˊ　ㄍㄨㄛˊ",
      "definitions": [
        {
          "def": "國名。位於非洲西部幾內亞灣內，接近赤道，由聖多美及普林西比兩島組成。面積九百六十四平方公里，人口約十二萬。首都為聖多美（Sao tome）。人民多信奉天主教，主要語言為葡語及多種方言。原屬葡萄牙，西元一九七五年七月十二日宣布獨立，訂七月十二日為國慶日。主要輸出品為可可、乾椰子肉、咖啡等。幣制為Dobra 。",
          "link": [
            "簡稱為「聖多美及普林西比」。"
          ]
        }
      ],
      "pinyin": "shèng duō měi jí pǔ lín xī bǐ mín zhǔ gòng hé guó"
    }
  ],
  "title": "聖多美及普林西比民主共和國（Democratic Republic of Sao Tome and Principt）"
}