{
  "heteronyms": [
    {
      "bopomofo": "ㄗㄡˇ　ㄐㄧㄤ　ㄏㄨˊ",
      "definitions": [
        {
          "def": "隱居江湖之間。",
          "quote": [
            "南朝宋．謝靈運〈會吟行〉：「范蠡走江湖，梅福入城市。」"
          ]
        }
      ],
      "pinyin": "zǒu jiāng hú"
    },
    {
      "bopomofo": "ㄗㄡˇ　ㄐㄧㄤ　˙ㄏㄨ",
      "definitions": [
        {
          "def": "舊指在各地奔走以獻演技藝混飯吃的人。",
          "quote": [
            "《儒林外史．第三回》：「就是周相公不還，我們走江湖的人，那裡不破掉了幾兩銀子！」",
            "《老殘遊記二編．第一回》：「我們走江湖的人，比不得你們做官的，我們那兒都可以混。」"
          ]
        }
      ],
      "pinyin": "zǒu jiāng hu"
    }
  ],
  "title": "走江湖"
}