{
  "heteronyms": [
    {
      "bopomofo": "ㄧ　ㄒㄧㄣ",
      "definitions": [
        {
          "def": "同心。",
          "example": [
            "如：「萬眾一心」。"
          ],
          "quote": [
            "《書經．泰誓上》：「予有臣三千，惟一心。」"
          ]
        },
        {
          "antonyms": "分心,多心,異志",
          "def": "專一其心、全心全意。",
          "example": [
            "如：「他一心想上大學。」"
          ],
          "quote": [
            "《孟子．告子上》：「一心以為有鴻鵠將至，思援弓繳而射之。」",
            "《文明小史．第三三回》：「縣官盛筵相待，說了無數的恭維話，一心要來籠絡。」"
          ],
          "synonyms": "專心"
        }
      ],
      "pinyin": "yī xīn"
    }
  ],
  "title": "一心"
}