{
  "heteronyms": [
    {
      "bopomofo": "ㄒㄧㄚˋ　ㄑㄩㄢˊ",
      "definitions": [
        {
          "def": "下流的泉水。",
          "quote": [
            "《詩經．曹風．下泉》：「洌彼下泉，浸彼苞稂。」",
            "《文選．陸機．文賦》：「浮天淵以安流，濯下泉而潛浸。」"
          ]
        },
        {
          "def": "黃泉。",
          "quote": [
            "《南史．卷五九．任昉傳》：「范、張款款於下泉，尹、班陶陶於永夕。」",
            "唐．白居易〈思舊〉詩：「再思今何在？零落歸下泉。」"
          ]
        },
        {
          "def": "《詩誙．曹風》的篇名。共四章。根據〈詩序〉：「下泉，思治也。」或以為是曹人讚美郇伯能勤勞王事之詩。首章二句為：「洌彼下泉，浸彼苞稂。」"
        }
      ],
      "pinyin": "xià quán"
    }
  ],
  "title": "下泉"
}