{
  "heteronyms": [
    {
      "bopomofo": "ㄒㄧㄢ　ㄧㄡˊ",
      "definitions": [
        {
          "def": "外出求仙訪道。",
          "quote": [
            "唐．李白〈感興〉詩六首之四：「十五遊神仙，仙遊未曾歇。」"
          ]
        },
        {
          "def": "稱人死亡。",
          "quote": [
            "《儒林外史．第八回》：「原來便是尊翁，怪道面貌相似，卻如何這般稱呼？  難道已仙遊了麼？」"
          ],
          "synonyms": "歸天,去世,仙逝,逝世,死亡,亡故"
        },
        {
          "def": "縣名。位於福建有東部，木蘭溪北岸。"
        }
      ],
      "pinyin": "xiān yóu"
    }
  ],
  "title": "仙遊"
}