{
  "heteronyms": [
    {
      "bopomofo": "ㄒㄧㄢ　ㄕㄥ",
      "definitions": [
        {
          "def": "對一般男子的尊稱。",
          "example": [
            "如：「陳先生」、「李先生」。"
          ]
        },
        {
          "def": "稱謂。妻子對他人稱自己的丈夫。",
          "example": [
            "如：「他跟我先生是多年的好友。」"
          ]
        },
        {
          "def": "對老師的尊稱。",
          "quote": [
            "《管子．弟子職》：「先生施教，弟子是則。」",
            "《初刻拍案驚奇．卷一三》：「延一個老成名師，擇日叫他拜了先生。」"
          ],
          "synonyms": "師長　3.老師"
        },
        {
          "def": "對年長有道德、有學問、或有專業技能者的尊稱。",
          "quote": [
            "《戰國策．宋衛策》：「乃見梧下先生，許之以百金。」",
            "《三國演義．第三四回》：「深感先生見愛。但凡人死生有命，豈馬所能妨哉！」"
          ],
          "synonyms": "師長　3.老師"
        },
        {
          "def": "對士人的稱呼。",
          "quote": [
            "《儀禮．士相見禮》：「若先生異爵者，請見之則辭，辭不得命，則曰某　無以見。」"
          ]
        },
        {
          "def": "對道士的稱呼。",
          "quote": [
            "明．賈仲名《金安壽．第一折》：「一個先生來化齋，求利市。」",
            "《警世通言．卷二八．白娘子永鎮雷峰塔》：「方出寺來，見一個先生，穿著道袍，頭戴逍　遙巾，腰繫黃絲絛，腳著熟麻鞋，坐在寺前賣藥，散施符水。」"
          ]
        },
        {
          "def": "妓女。",
          "quote": [
            "《海上花列傳．第四回》：「王老爺！耐勿來仔末，倪先生氣得來，害倪一埭一埭　來請耐。」",
            "《文明小史．第一九回》：「上海妓女，都是稱先生的。」"
          ]
        }
      ],
      "pinyin": "xiān shēng"
    }
  ],
  "title": "先生"
}