{
  "heteronyms": [
    {
      "bopomofo": "ㄔㄨ　ㄎㄡˇ",
      "definitions": [
        {
          "antonyms": "進口　5.入口",
          "def": "將本國貨物運到外國。如：「香蕉、樟腦等是臺灣出口的大宗。」也作「輸出」。"
        },
        {
          "def": "赴張家口以北等邊塞之地。",
          "quote": [
            "《兒女英雄傳．第四○回》：「一出口連個住處沒有，一天二百里，好容易盼到站了，得住那個惡臭的蒙古包。」"
          ]
        },
        {
          "def": "清代遣戍犯人至關外，稱為「出口」。",
          "quote": [
            "《官場現形記．第四八回》：「將來他三人的罪名，重則殺頭，輕則出口。」"
          ]
        },
        {
          "def": "出言。",
          "quote": [
            "《紅樓夢．第五六回》：「這件事須得姑娘說出來，我們奶奶雖有此心，也未必好出口。」",
            "《文明小史．第一一回》：「因為這事自己不便出口，只好託師爺把首縣請來，同他商量。」"
          ]
        },
        {
          "antonyms": "進口　5.入口",
          "def": "外出的門。相對於入口而言。",
          "example": [
            "如：「下車後我會在火車站出口等你。」"
          ]
        },
        {
          "def": "船隻駛出港口。",
          "quote": [
            "《文明小史．第二四回》：「次日出口，風平浪靜，兩人憑欄看看海中景緻。」"
          ]
        }
      ],
      "pinyin": "chū kǒu"
    }
  ],
  "title": "出口"
}