{
  "heteronyms": [
    {
      "bopomofo": "ㄉㄨㄛˋ　ㄐㄧㄝˋ",
      "definitions": [
        {
          "def": "嘆息。",
          "quote": [
            "《抱朴子．勤求》：「令人怛然心熱，不覺咄嗟。」",
            "宋．梅堯臣〈范饒州坐中客語食河豚魚〉詩：「吾語不能屈，自思空咄嗟。」"
          ]
        },
        {
          "def": "片刻之間。",
          "quote": [
            "《文選．左思．詠史詩八首之八》：「俛仰生榮華，咄嗟復彫枯。」",
            "《醒世恆言．卷七．錢秀才錯占鳳凰儔》：「三湯十菜，添案小喫，頃刻間，擺滿了桌子，真個咄嗟而辦。」"
          ]
        },
        {
          "def": "呵叱、怒吼。",
          "quote": [
            "宋．蘇轍〈三國論〉：「項籍乘百戰百勝之威而執諸侯之柄，咄嗟叱吒，奮其暴怒。」"
          ]
        }
      ],
      "pinyin": "duò jiè"
    }
  ],
  "title": "咄嗟"
}