{
  "heteronyms": [
    {
      "bopomofo": "ㄏㄨㄟˊ　ㄓㄨㄢˇ",
      "definitions": [
        {
          "def": "反覆輪轉。",
          "quote": [
            "《後漢書．卷五八．虞詡傳》：「明日悉陳其兵眾，令從東郭門出，北郭門入，貿易衣服，回轉數周。」"
          ],
          "synonyms": "展轉"
        },
        {
          "def": "返回。《永樂大典戲文三種．小孫屠．第一一出》：「昨日我萱親去燒香，卑人送到半途回轉。」也作「回旋」。"
        },
        {
          "def": "掉轉。",
          "quote": [
            "《水滸傳．第一○三回》：「張世開聽得後面腳步響，回轉頭來。」"
          ]
        },
        {
          "def": "心回意轉。《紅樓夢．第六二回》：「讓我收起來，過兩日他自然回轉過來了。」也作「迴轉」。"
        }
      ],
      "pinyin": "huí zhuǎn"
    }
  ],
  "title": "回轉"
}