{
  "heteronyms": [
    {
      "bopomofo": "ㄋㄧㄤˊㄦ",
      "definitions": [
        {
          "def": "稱謂：(1) 北平地區稱姑姑為娘兒。(2) 稱長一輩的女性親戚。"
        },
        {
          "def": "婦女。",
          "quote": [
            "《紅樓夢．第一一回》：「你們娘兒兩個忒好了，見了面，總捨不得來了。」"
          ]
        }
      ],
      "pinyin": "niángr"
    },
    {
      "bopomofo": "ㄋㄧㄤˊ　ㄦˊ",
      "definitions": [
        {
          "def": "母親和子女。",
          "quote": [
            "元．關漢卿《竇娥冤．楔子》：「止有一個孩兒，年長八歲，俺娘兒兩個，過其日月。」",
            "《紅樓夢．第三五回》：「何苦來。為我一個人，娘兒兩個天天操心。」"
          ]
        }
      ],
      "pinyin": "niáng ér"
    }
  ],
  "title": "娘兒"
}