{
  "heteronyms": [
    {
      "bopomofo": "ㄖㄨㄥˊ　ㄧˋ",
      "definitions": [
        {
          "def": "水流蕩漾的樣子。",
          "quote": [
            "三國魏．曹丕〈濟川賦〉：「臨濟川之魯淮，覽洪波之容裔。」",
            "宋．洪邁《容齋四筆．卷四．會合聯句》：「維水容裔，維山巃嵸。」"
          ]
        },
        {
          "def": "隨風飄蕩。",
          "quote": [
            "《文選．張衡．東京賦》：「建辰旒之太常，紛焱悠以容裔。」",
            "南朝宋．謝莊　〈懷園引〉：「還流兮潺湲，歸煙容裔去不旋。」"
          ]
        },
        {
          "def": "從容自適。",
          "quote": [
            "《文選．左思．吳都賦》：「翕習容裔，靡靡愔愔。」",
            "《文選．江淹．雜體詩．謝光祿》：「行光自容裔，無使弱思侵。」"
          ]
        }
      ],
      "pinyin": "róng yì"
    }
  ],
  "title": "容裔"
}