{
  "heteronyms": [
    {
      "bopomofo": "ㄏㄢˊ　ㄩˋ",
      "definitions": [
        {
          "def": "玉質清冷，故稱玉為「寒玉」。",
          "quote": [
            "唐．白居易〈苦熱中寄舒員外〉詩：「藤床鋪晚雪，角枕截寒玉。」"
          ]
        },
        {
          "def": "比喻清冷雅潔的東西。如明月、溪水、寒竹等。",
          "quote": [
            "唐．雍陶〈韋處士郊居〉詩：「門外晚晴秋色老，萬條寒玉一溪煙。」",
            "唐．李群玉〈引水行〉：「一條寒玉走秋泉，引出深蘿洞口煙。」"
          ]
        },
        {
          "def": "比喻容貌清俊。",
          "quote": [
            "唐．貫休〈題淮南惠照寺律師院〉詩：「儀冠凝寒玉，端居似沃州。」"
          ]
        }
      ],
      "pinyin": "hán yù"
    }
  ],
  "title": "寒玉"
}