{
  "heteronyms": [
    {
      "bopomofo": "ㄕˊ　ㄌㄨˋ",
      "definitions": [
        {
          "def": "據實的記載。",
          "quote": [
            "《漢書．卷六二．司馬遷傳．贊曰》：「其文直，其事核，不虛美，不隱惡，故謂之實錄。」",
            "《文選．曹植．與楊德祖書》：「則將采庶官之實錄，辯時俗之得失。」"
          ]
        },
        {
          "def": "史體的一種。於一帝崩後，取其起居注、日錄、時政記等記注之作，並詔令章奏等，年經月緯，彙而成編。如《隋書經籍志》著錄有周興嗣梁皇帝實錄三卷，記武帝事。"
        },
        {
          "def": "記述私人事跡的著作。如《四庫提要》、史部傳記類存目有孔氏實錄一卷，不著撰人名氏　。"
        }
      ],
      "pinyin": "shí lù"
    }
  ],
  "title": "實錄"
}