{
  "heteronyms": [
    {
      "bopomofo": "ㄕㄢ　ㄌㄧㄥˊ",
      "definitions": [
        {
          "def": "山岳岡陵。",
          "quote": [
            "《禮記．月令》：「可以居高明，可以遠眺望，可以升山陵，可以處臺榭。」",
            "《文選．司馬相如．上林賦》：「千人唱萬人和，山陵為之震動，川谷為之蕩波。」"
          ]
        },
        {
          "def": "指帝王。",
          "quote": [
            "《戰國策．秦策五》：「王之春秋高，一日山陵崩，太子用事，君危於累卵，而不壽於朝生。」"
          ]
        },
        {
          "def": "帝王的墳墓。",
          "quote": [
            "南朝梁．劉勰《文心雕龍．祝盟》：「漢代山陵，哀策流文，周喪盛姬，　內史執策。」"
          ]
        }
      ],
      "pinyin": "shān líng"
    }
  ],
  "title": "山陵"
}