{
  "heteronyms": [
    {
      "bopomofo": "ㄕ　ㄖㄣˊ",
      "definitions": [
        {
          "def": "士兵。",
          "quote": [
            "《左傳．宣公十二年》：「申公巫臣曰：『師人多寒。』王巡三軍，拊而勉之。」",
            "《魏書．卷六○．韓麒麟傳》：「後參征南慕容白曜軍事，進攻升城，師人多傷。」"
          ]
        },
        {
          "def": "巫師、星相等術士。",
          "quote": [
            "宋．俞琰《書齋夜話．卷一》：「南方俚俗稱巫為太保，又呼為師人。」",
            "《水滸傳．第六一回》：「寧可信其有，不可信其無。自古禍出師人口，必主吉凶。」"
          ]
        }
      ],
      "pinyin": "shī rén"
    }
  ],
  "title": "師人"
}