{
  "heteronyms": [
    {
      "bopomofo": "ㄔㄤˊ　ㄈㄨˊ",
      "definitions": [
        {
          "antonyms": "禮服",
          "def": "日常穿的便服。",
          "quote": [
            "《南史．卷五．齊廢帝東昏侯本紀》：「戎服急裝縛褲，上著絳衫，以為常服，不變寒暑。」",
            "宋．蘇軾〈贈寫御客妙善〉詩：「幅巾常服儼不動，孤臣入門涕自滂。」"
          ]
        },
        {
          "def": "古代軍隊裡所穿的制服。",
          "quote": [
            "《詩經．小雅．六月》：「四牡騤騤，載是常服。」",
            "漢．毛亨．傳：「常服，戎服也。」",
            "《左傳．閔公二年》：「帥師者受命於廟，受脤於社，有常服矣。」"
          ]
        }
      ],
      "pinyin": "cháng fú"
    }
  ],
  "title": "常服"
}