{
  "heteronyms": [
    {
      "bopomofo": "ㄅㄚˇ　ㄨㄛˋ",
      "definitions": [
        {
          "def": "握手、互相執手。",
          "quote": [
            "晉．程本《子華子．神氣》：「今世之人，其平居把握附耳，呫呫相為然約而自保。」"
          ]
        },
        {
          "def": "掌握。",
          "example": [
            "如：「把握機會」、「把握光陰」。"
          ]
        },
        {
          "def": "成功的信心。",
          "quote": [
            "《文明小史．第五三回》：「如果怕沒有把握，何妨到上海去先會會那位礦師和他訂張合同。」"
          ]
        },
        {
          "def": "一握。",
          "quote": [
            "《國語．楚語下》：「王曰：『其大小何如？』對曰：『郊禘不過繭栗，烝嘗不過把握。』」"
          ]
        }
      ],
      "pinyin": "bǎ wò"
    }
  ],
  "title": "把握"
}