{
  "heteronyms": [
    {
      "bopomofo": "ㄓㄨㄞˋ　ㄊㄚ",
      "definitions": [
        {
          "def": "倒塌。",
          "quote": [
            "元．張國賓《合汗衫．第二折》：「我則見連天的大廈、大廈、聲剌剌，被巡軍橫拽塌。」",
            "元．湯式〈普天樂．錢唐懷古〉曲：「總是當年題詩處，料應來滿目荒蕪，亭臺拽塌。」"
          ]
        },
        {
          "def": "糟蹋。",
          "quote": [
            "元．武漢臣《玉壺春．第四折》：「量你個野蜂兒，怎調和蜂蜜？頹氣了惜花春起早，拽塌了愛月夜眠遲，強風情不曉事。」"
          ]
        },
        {
          "def": "收拾起。",
          "quote": [
            "元．無名氏〈慶東原．難收救〉曲：「私情兒拽塌，好話兒填扎。猶兀自保兒嗔，斷不了姨夫罵。」"
          ]
        }
      ],
      "pinyin": "zhuài tā"
    }
  ],
  "title": "拽塌"
}