{
  "heteronyms": [
    {
      "bopomofo": "ㄕˊ　ㄐㄧㄝˊ",
      "definitions": [
        {
          "def": "季節、節令。",
          "quote": [
            "《文選．古詩十九首．明月皎夜光》：「白露沾野草，時節忽復易。」",
            "唐．杜牧〈清明〉詩：「清明時節雨紛紛，路上行人欲斷魂。」"
          ]
        },
        {
          "def": "節日。",
          "quote": [
            "《三國志．卷三五．蜀書．諸葛亮傳》：「詔為亮立廟於沔陽」句下裴松之注引〈襄陽記〉：「百始遂因時節，私祭之於道陌上。」",
            "清．孔尚任《桃花扇．第五齣》：「每遇時節，便做盛會。」"
          ]
        },
        {
          "def": "合時、適時。",
          "quote": [
            "《漢書．卷二八．地理志下》：「風雨時節，穀糴常賤。」"
          ]
        },
        {
          "def": "時刻、時候。",
          "quote": [
            "唐．杜甫〈江南逢李龜年〉詩：「正是江南好風景，落花時節又逢君。」",
            "《文明小史．第四一回》：「那時節正是少年氣盛，不曉得什麼世路高低 。」"
          ]
        }
      ],
      "pinyin": "shí jié"
    }
  ],
  "title": "時節"
}