{
  "heteronyms": [
    {
      "bopomofo": "ㄔㄠˊ　ㄊㄧㄥˊ",
      "definitions": [
        {
          "def": "君主視事聽政的地方。",
          "quote": [
            "《儒林外史．第四五回》：「他而今官大了，是翰林院大學士，又帶著左春坊，每日就要站在朝廷大堂上暖閣子裡議事。」"
          ]
        },
        {
          "def": "君主時代的政府。",
          "quote": [
            "《三國演義．第二回》：「朝廷加皇甫嵩為車騎將軍，領冀州牧。」",
            "《文明小史．第一七回》：「說什麼朝廷指日就要把八股全然廢掉，又說什麼專考策論。」"
          ]
        },
        {
          "def": "皇帝。",
          "quote": [
            "《後漢書．卷六六．王允傳》：「朝廷幼小，恃我而己，臨難苟免，吾不忍也。」",
            "《儒林外史．第四五回》：「聽見前日辭朝的時候，他一句話回的不好，朝廷把他身子拍了一下。」"
          ]
        }
      ],
      "pinyin": "cháo tíng"
    }
  ],
  "title": "朝廷"
}