{
  "heteronyms": [
    {
      "bopomofo": "ㄌㄧㄡˊ　ㄊㄨㄥ",
      "definitions": [
        {
          "antonyms": "阻塞",
          "def": "運行未受阻礙。",
          "example": [
            "如：「請保持空氣流通。」"
          ],
          "quote": [
            "《後漢書．卷八二．方術列傳下．華佗》：「動搖則穀氣得銷，血脈流通，病不得生。」"
          ],
          "synonyms": "暢通"
        },
        {
          "def": "指交換財貨、互通有無。",
          "quote": [
            "《晉書．卷二六．食貨志》：「西域人入貢，財貨流通，皆邈之功也。」",
            "《文明小史》第四八回：「遠近的匯兌，到處可以流通。」"
          ]
        }
      ],
      "pinyin": "liú tōng"
    }
  ],
  "title": "流通"
}