{
  "heteronyms": [
    {
      "bopomofo": "ㄏㄨㄣˊ　ㄐㄧㄚ",
      "definitions": [
        {
          "def": "全家。",
          "quote": [
            "宋．尤袤〈淮民謠〉：「無錢買刀劍，典盡渾家衣。」",
            "元．無名氏《飛刀對箭．第二折》：「我渾家大小七八十口人，打著千斤望下墜，也不曾墜的這弓開一些兒。」"
          ]
        },
        {
          "def": "妻子。",
          "quote": [
            "元．張國賓《看錢奴．第二折》：「小生周祖榮，嫡親的三口兒家屬，渾家張氏，孩兒長壽。」",
            "《警世通言．卷一二．范鰍兒雙鏡重圓》：「我已別娶渾家，舊日伉儷之盟，不必再題。」"
          ]
        }
      ],
      "pinyin": "hún jiā"
    }
  ],
  "title": "渾家"
}