{
  "heteronyms": [
    {
      "bopomofo": "ㄖㄨㄥˊ　ㄖㄨㄥˊ",
      "definitions": [
        {
          "def": "水勢盛大的樣子。",
          "quote": [
            "南朝梁．江淹〈哀千里賦〉：「水則遠天相逼，浮雲共色，茫茫無底，溶溶不測。」",
            "唐．杜牧〈阿房宮賦〉：「二川溶溶，流入宮牆。」"
          ]
        },
        {
          "def": "寬廣的樣子。",
          "quote": [
            "《楚辭．劉向．九歎．愍命》：「心溶溶其不可量兮，情澹澹其若淵。」"
          ]
        },
        {
          "def": "盛多的樣子。",
          "quote": [
            "唐．皇甫湜〈吉州刺史廳壁記〉：「瑞露溶溶，降味公松。」",
            "清．洪昇《長生殿．第三二齣》：「淚珠兒溶溶滿觴，怕添不下半滴葡萄釀。」"
          ]
        },
        {
          "def": "明淨且潔白的樣子。",
          "quote": [
            "唐．許渾〈冬日宣城開元寺贈元孚上人〉詩：「林疏霜摵摵，波靜月溶溶。」"
          ]
        },
        {
          "def": "暖和。",
          "quote": [
            "宋．晏殊〈採桑子．陽和二月芳菲遍〉詞：「陽和二月芳菲遍，暖景溶溶。」",
            "宋．蘇軾〈哨遍．睡起畫堂〉詞：「初雨歇，洗出碧羅天，正溶溶養花天氣。」"
          ]
        }
      ],
      "pinyin": "róng róng"
    }
  ],
  "title": "溶溶"
}