{
  "heteronyms": [
    {
      "bopomofo": "ㄌㄡˋ　ㄓ",
      "definitions": [
        {
          "def": "古代一種有漏孔的圓形盛酒器。",
          "quote": [
            "漢．桓寬《鹽鐵論．本議》：「故川源不能實漏巵，山海不能贍溪壑。」",
            "《文選．曹植．與吳季重書》：「食若填巨壑，飲若灌漏巵。」"
          ]
        },
        {
          "def": "漏洞。",
          "quote": [
            "《福惠全書．卷六．錢穀部．總論》：「至于漕項，惟收之便民而塞倉中之漏巵。」"
          ]
        },
        {
          "def": "豪飲之士。",
          "quote": [
            "《洛陽伽藍記．卷三．報德寺》：「肅初入國，不食羊肉及酪漿等物，常飯鯽魚羹，渴飲茗汁，京師士子道肅一飲一斗，號為『漏巵』。」"
          ]
        },
        {
          "def": "比喻權力外溢。"
        }
      ],
      "pinyin": "lòu zhī"
    }
  ],
  "title": "漏巵"
}