{
  "heteronyms": [
    {
      "bopomofo": "ㄇㄛˋ　ㄇㄛˋ",
      "definitions": [
        {
          "def": "寂靜無聲。",
          "quote": [
            "宋．秦觀〈浣溪沙．漠漠輕寒〉詞：「漠漠輕寒上小樓，曉陰無賴似窮秋。」",
            "宋．蘇軾〈漁父．漁父笑〉詞：「漁父笑，輕鷗舉，漠漠一家風雨。」"
          ]
        },
        {
          "def": "密布羅列的樣子。",
          "quote": [
            "唐．王維〈積雨輞川莊作〉詩：「漠漠水田飛白鷺，陰陰夏木囀黃鸝。」",
            "唐．韋應物〈賦得暮雨送李曹〉詩：「漠漠帆來重，冥冥鳥來遲。」"
          ]
        },
        {
          "def": "分散布列的樣子。",
          "quote": [
            "南朝齊．謝朓〈游東田〉詩：「遠樹曖阡阡，生煙紛漠漠。」",
            "宋．陸游〈病起〉詩：「斷香漠漠便支枕，芳草離離悔倚闌。」"
          ]
        },
        {
          "def": "昏暗的樣子。",
          "quote": [
            "唐．杜甫〈秋日夔府詠懷奉寄鄭監李賓客一百韻〉：「兵戈塵漠漠，江漢月娟娟。」"
          ]
        }
      ],
      "pinyin": "mò mò"
    }
  ],
  "title": "漠漠"
}