{
  "heteronyms": [
    {
      "bopomofo": "ㄙㄨㄟ　ㄙㄨㄟ",
      "definitions": [
        {
          "def": "走路遲緩的樣子。",
          "quote": [
            "《詩經．衛風．有狐》：「有狐綏綏，在彼淇梁。」"
          ]
        },
        {
          "def": "安泰的樣子。",
          "quote": [
            "《荀子．儒效》：「綏綏兮其有文章也。」"
          ]
        },
        {
          "def": "落下的樣子。",
          "quote": [
            "宋．梅堯臣〈五月十日雨中飲〉詩：「梅天下梅雨，綏綏如亂麻。」"
          ]
        }
      ],
      "pinyin": "suī suī"
    }
  ],
  "title": "綏綏"
}