{
  "heteronyms": [
    {
      "bopomofo": "ㄌㄨㄛˋ　ㄌㄨㄛˋ",
      "definitions": [
        {
          "def": "形容高、眾多或稀疏等現象的狀態詞。",
          "quote": [
            "《文選．陸機．歎逝賦》：「親落落而日稀，友靡靡而愈索。」",
            "唐．杜甫〈古柏行〉：「落落盤踞雖得地，冥冥孤高多烈風。」"
          ]
        },
        {
          "def": "形容舉止瀟灑自然，心胸曠達率真。",
          "quote": [
            "《晉書．卷一○五．石勒載記下》：「大丈夫行事當礌礌落落，如日月皎然。」"
          ]
        },
        {
          "def": "形容對人冷淡，與人合不來。",
          "example": [
            "如：「落落寡合」。"
          ],
          "quote": [
            "晉．左思〈詠史詩〉八首之八：「落落窮巷士，抱影守空廬。」"
          ]
        },
        {
          "def": "淪落、衰敗的樣子。",
          "quote": [
            "宋．文天祥〈過零丁洋〉詩：「辛苦遭逢起一經，干戈落落四周星 。」",
            "《聊齋志異．卷一．葉生》：「行蹤落落，對影長愁。」"
          ]
        }
      ],
      "pinyin": "luò luò"
    }
  ],
  "title": "落落"
}