{
  "heteronyms": [
    {
      "bopomofo": "ㄒㄧㄥˊ　ㄌㄧˇ",
      "definitions": [
        {
          "def": "以鞠躬、作揖等方式表達敬意。",
          "quote": [
            "《禮記．曲禮下》：「君子行禮，不求變俗。」",
            "《紅樓夢．第六二回》：「雖眾人要行禮，也不曾受。」"
          ],
          "synonyms": "見禮,施禮"
        },
        {
          "def": "舉行某種儀式。",
          "quote": [
            "《初刻拍案驚奇．卷五》：「與他家往來得熟，其日因為他家成婚行禮，　也來看看耍子。」",
            "《儒林外史．第三七回》：「先一日就請老先生到來祠中齋戒一宿，　以便行禮。」"
          ]
        }
      ],
      "pinyin": "xíng lǐ"
    }
  ],
  "title": "行禮"
}