{
  "heteronyms": [
    {
      "bopomofo": "ㄔㄨㄥ　ㄉㄨㄥˋ",
      "definitions": [
        {
          "antonyms": "冷靜,抑制",
          "def": "因情緒過於激動，而訴諸非理性的心理活動。",
          "example": [
            "如：「他因一時衝動，鑄成大錯。」"
          ],
          "synonyms": "激動"
        },
        {
          "def": "勾引、誘惑。",
          "quote": [
            "元．關漢卿《救風塵．第三折》：「我這等打扮，可衝動得那廝麼？」",
            "元．王實甫《西廂記．第五本．第三折》：「休說別個，只這一套衣服也衝動他。」"
          ]
        },
        {
          "def": "衝撞撼動。",
          "quote": [
            "《三國演義．第七○回》：「張郃軍兵，反被自家敗兵衝動，都屯紮不住，望後而走。」",
            "《東周列國志．第九回》：「陳兵原無鬥志，即時奔散，反將周兵衝動。」"
          ]
        }
      ],
      "pinyin": "chōng dòng"
    }
  ],
  "title": "衝動"
}