{
  "heteronyms": [
    {
      "bopomofo": "ㄓㄣˋ　ㄉㄧㄥˋ",
      "definitions": [
        {
          "def": "使安定、平靜。",
          "quote": [
            "《國語．晉語七》：「柔惠小物，而鎮定大事。」",
            "《文明小史．第四三回》：「二來現在謠言雖定，人心不免狐疑，大帥去走一趟，也可以鎮定鎮定人心。」"
          ]
        },
        {
          "antonyms": "發慌,恐慌,駭怕,慌亂,慌張,激動,緊張,驚慌,驚惶,顫慄,倉皇",
          "def": "沉著穩定，臨事不亂。",
          "example": [
            "如：「出了這麼多狀況，他還是非常鎮定，按部就班，照原定計畫進行。」"
          ],
          "synonyms": "冷靜,鎮靜,沉著"
        }
      ],
      "pinyin": "zhèn dìng"
    }
  ],
  "title": "鎮定"
}