{
  "heteronyms": [
    {
      "bopomofo": "ㄐㄧㄝ　ㄊㄧ",
      "definitions": [
        {
          "def": "層層高起的臺階。",
          "example": [
            "如：「沿著階梯往上走，你就可以看到一座寺廟。」"
          ],
          "quote": [
            "南朝梁．何遜  〈七召八首之二．宮室〉：「百丈杳冥以飛跨，九層鬱律以階梯。」"
          ]
        },
        {
          "def": "事情發生的原由。",
          "quote": [
            "《易經．繫辭上》唐．孔穎達．正義：「言亂之所生，則由言語以為亂之　階梯也。」"
          ]
        },
        {
          "def": "門路、途徑。",
          "example": [
            "如：「這可是升官的階梯，好好把握。」"
          ],
          "synonyms": "門路"
        }
      ],
      "pinyin": "jiē tī"
    }
  ],
  "title": "階梯"
}