{
  "heteronyms": [
    {
      "bopomofo": "ㄌㄡˋ　ㄊㄡˊ",
      "definitions": [
        {
          "def": "出現。",
          "example": [
            "如：「他一在街上露頭，就被警方逮捕。」"
          ]
        },
        {
          "def": "比喻出人頭地。",
          "example": [
            "如：「十年苦讀，終會有露頭的一天。」"
          ]
        }
      ],
      "pinyin": "lòu tóu"
    },
    {
      "bopomofo": "ㄌㄨˋ　ㄊㄡˊ",
      "definitions": [
        {
          "def": "顯露在地表的岩層、礦脈。",
          "link": [
            "也稱為「露苗」。"
          ]
        }
      ],
      "pinyin": "lù tóu"
    }
  ],
  "title": "露頭"
}